wiki_template/__init__.py
wiki_template/admin.py
wiki_template/apps.py
wiki_template/forms.py
wiki_template/markdown_extensions.py
wiki_template/models.py
wiki_template/settings.py
wiki_template/tests.py
wiki_template/views.py
wiki_template/wiki_plugin.py
wiki_template/locale/en/LC_MESSAGES/django.po
wiki_template/locale/zh_CN/LC_MESSAGES/django.po
wiki_template/migrations/0001_initial.py
wiki_template/migrations/__init__.py
wiki_template/templates/wiki_template/delete.html
wiki_template/templates/wiki_template/history.html
wiki_template/templates/wiki_template/index.html
wiki_template/templates/wiki_template/render.html
wiki_template/templates/wiki_template/revision_add.html
wiki_template/templates/wiki_template/search.html
wiki_template/templates/wiki_template/sidebar.html
wiki_template/templates/wiki_template/template_create.html
wiki_template-0.2.dist-info/DESCRIPTION.rst
wiki_template-0.2.dist-info/METADATA
wiki_template-0.2.dist-info/RECORD
wiki_template-0.2.dist-info/WHEEL
wiki_template-0.2.dist-info/metadata.json
wiki_template-0.2.dist-info/top_level.txt
