Metadata-Version: 2.0
Name: wiki-template
Version: 0.2
Summary: A django-wiki plugin that MediaWiki style template implemented.
Home-page: https://github.com/tkliuxing/wiki-template
Author: Ronald White
Author-email: UNKNOWN
License: GPLv3
Keywords: wiki,template
Platform: UNKNOWN
Classifier: Development Status :: 3 - Alpha
Classifier: License :: OSI Approved :: GNU General Public License v3 (GPLv3)
Classifier: Environment :: Web Environment
Classifier: Framework :: Django
Classifier: Intended Audience :: Developers
Classifier: Operating System :: OS Independent
Classifier: Programming Language :: Python
Classifier: Programming Language :: Python :: 2.6
Classifier: Programming Language :: Python :: 2.7
Classifier: Programming Language :: Python :: 3.3
Classifier: Programming Language :: Python :: 3.4
Requires-Dist: wiki (>=0.1)
